ezfintech/__init__.py
ezfintech/stockAnalysis.py
ezfintech/stockData.py
ezfintech/stockKnowledge.py
ezfintech/stockVisualization.py
ezfintech/stockModels/EZLSTM.py
ezfintech/stockModels/__init__.py
ezfintech-0.0.331.dist-info/LICENSE
ezfintech-0.0.331.dist-info/METADATA
ezfintech-0.0.331.dist-info/WHEEL
ezfintech-0.0.331.dist-info/top_level.txt
ezfintech-0.0.331.dist-info/RECORD
