Metadata-Version: 2.1
Name: ezfintech
Version: 0.0.331
Summary: get stock data from different APIs and Analyze Stock Data
Home-page: https://github.com/YizheZhang-Ervin/EZFintech
Author: Yizhe Zhang
Author-email: ervinzhang319@gmail.com
License: MIT
Platform: UNKNOWN
Classifier: Programming Language :: Python :: 3
Classifier: License :: OSI Approved :: MIT License
Classifier: Operating System :: OS Independent
Requires-Dist: numpy
Requires-Dist: pandas
Requires-Dist: matplotlib
Requires-Dist: requests
Requires-Dist: mplfinance
Requires-Dist: pandas-datareader
Requires-Dist: tensorflow
Requires-Dist: scipy
